setup.py
docs/HISTORY
docs/LICENSE
docs/README
twisted/__init__.py
twisted.scheduling.egg-info/PKG-INFO
twisted.scheduling.egg-info/SOURCES.txt
twisted.scheduling.egg-info/dependency_links.txt
twisted.scheduling.egg-info/namespace_packages.txt
twisted.scheduling.egg-info/not-zip-safe
twisted.scheduling.egg-info/requires.txt
twisted.scheduling.egg-info/top_level.txt
twisted/scheduling/__init__.py
twisted/scheduling/cron.py
twisted/scheduling/interfaces.py
twisted/scheduling/task.py
twisted/scheduling/tests/__init__.py
twisted/scheduling/tests/cron.py
twisted/scheduling/tests/task.py