Metadata-Version: 1.0
Name: twisted.scheduling
Version: 1.0
Summary: A scheduling plugin for twisted
Home-page: http://code.google.com/p/meercat
Author: Benjamin Liles
Author-email: bliles@library.tamu.edu
License: UNKNOWN
Keywords: twisted python scheduling cron
Platform: UNKNOWN
Classifier: Programming Language :: Python
Classifier: Framework :: Twisted
Classifier: Development Status :: 4 - Beta
Classifier: Intended Audience :: Developers
Classifier: License :: OSI Approved :: Apache Software License
Classifier: Topic :: Software Development :: Libraries :: Application Frameworks
Classifier: Topic :: Software Development :: Libraries :: Python Modules
